{
  "preRequisites:11": [
    550
  ],
  "properties:10": {
    "betterquesting:10": {
      "desc:8": "susy.quest.db.755.desc",
      "icon:10": {
        "Damage:2": 15124,
        "id:8": "gregtech:meta_plate"
      },
      "name:8": "susy.quest.db.755.title"
    }
  },
  "questID:3": 755,
  "tasks:9": {
    "0:10": {
      "requiredItems:9": {
        "0:10": {
          "Count:3": 16,
          "Damage:2": 15124,
          "id:8": "gregtech:meta_plate"
        }
      },
      "taskID:8": "bq_standard:retrieval"
    }
  }
}